{
  "title": "At Nitish Kumar’s Bihar Cabinet’s oath-taking ceremony, PM Modi waves Bihari ‘gamchha’ in signature style: WATCH",
  "text": "In this screengrab from a video posted on Nov. 20, 2025, Prime Minister Narendra Modi with newly sworn-in Bihar Chief Minister Nitish Kumar, state Ministers Samrat Choudhary and Vijay Kumar Sinha during the swearing-in ceremony, at Gandhi Maidan in Patna. (PTI Photo)\n\nPrime Minister Narendra Modi Thursday expressed his gratitude to the people of Bihar for giving the National Democratic Alliance (NDA) the biggest political mandate in the Assembly elections since 2010, by waving his ‘gamchha’ in signature style, a gesture which has gone viral on social media.\n\nModi arrived at Patna’s Gandhi Maidan today to attend the swearing-in ceremony of Nitish Kumar as the Bihar Chief Minister for a record 10th time. Alongside Nitish, Bharatiya Janata Party (BJP) leaders Samrat Choudhary and Vijay Kumar Sinha also took oath as Bihar ministers.",
  "summary": "",
  "published": "Thu, 20 Nov 2025 08:31:54 +0000",
  "url": "https://indianexpress.com/article/india/nitish-kumar-cabinet-oath-taking-ceremony-pm-modi-bihari-gamchha-signature-style-watch-10375891/",
  "source": "India | The Indian Express"
}