{
  "title": "Smith's swipe at Panesar comments on eve of Ashes",
  "text": "Steve Smith marked his temporary return as Australia's Ashes captain with a bizarre attack on former England spinner Monty Panesar.\n\nPanesar recently called on travelling fans and media to barrack Smith over his role in the 'Sandpapergate' ball-tampering scandal seven years ago, saying he should be made to feel \"guilty\" about standing in as Pat Cummins' replacement skipper.\n\nREAD MORE: Smith aims bizarre jibe at former spinner Panesar",
  "summary": "Steve Smith marks his temporary return as Australia's Ashes captain with a bizarre attack on ex-England spinner Monty Panesar.",
  "published": "Thu, 20 Nov 2025 07:56:24 GMT",
  "url": "https://www.bbc.com/sport/cricket/videos/ce3k3k9p2gpo?at_medium=RSS&at_campaign=rss",
  "source": "BBC Sport"
}